test/__init__.py
test/combined_time_set_test.py
test/explicit_time_set_test.py
test/lint_test.py
test/singleton_time_set_test.py
test/utils.py
tzolkin/__init__.py
tzolkin/asynchronous_schedule.py
tzolkin/command_grammar.py
tzolkin/job.py
tzolkin/schedule.py
tzolkin/synchronous_schedule.py
tzolkin/time_set.py
tzolkin/time_set_builder.py
tzolkin/time_sets.py
tzolkin/tzolktab.py
tzolkin-1.0.1.data/scripts/tzolk
tzolkin-1.0.1.dist-info/LICENSE
tzolkin-1.0.1.dist-info/METADATA
tzolkin-1.0.1.dist-info/WHEEL
tzolkin-1.0.1.dist-info/top_level.txt
tzolkin-1.0.1.dist-info/RECORD
