Metadata-Version: 2.1
Name: tzolkin
Version: 1.0.1
Summary: Scheduling for humans
License: Copyright 2022
Keywords: schedule,time,cron
Classifier: License :: OSI Approved :: MIT License
Classifier: Programming Language :: Python
Classifier: Programming Language :: Python :: 3
Requires-Python: >=3.9
License-File: LICENSE
Requires-Dist: attrs
Requires-Dist: croniter
Requires-Dist: maya
Requires-Dist: parsimonious
Requires-Dist: pytimeparse
Requires-Dist: snaptime
Requires-Dist: sortedcontainers
Provides-Extra: dev
Requires-Dist: build ; extra == 'dev'
Requires-Dist: hypothesis ; extra == 'dev'
Requires-Dist: pytest ; extra == 'dev'
Requires-Dist: tidypy ; extra == 'dev'
Requires-Dist: twine ; extra == 'dev'
